pyoutline.py
pyoutline_tools.py
pyoutline-0.4.dist-info/LICENSE
pyoutline-0.4.dist-info/METADATA
pyoutline-0.4.dist-info/WHEEL
pyoutline-0.4.dist-info/entry_points.txt
pyoutline-0.4.dist-info/top_level.txt
pyoutline-0.4.dist-info/RECORD
