Metadata-Version: 2.1
Name: pyoutline
Version: 0.4
Summary: A simple CLI app to run Outline VPN keys
Home-page: https://github.com/NonProjects/pyoutline
Download-URL: https://github.com/NonProjects/pyoutline/archive/refs/tags/v0.4.tar.gz
Author: NonProjects
Author-email: thenonproton@pm.me
License: MIT
License-File: LICENSE
Requires-Dist: click
Requires-Dist: nonshadowsocks
